bitmast_blockcypher/__init__.py
bitmast_blockcypher/datastructures.py
bitmast_blockcypher/util.py
bitmast_blockcypher/blockchain/__init__.py
bitmast_blockcypher/config/.gitkeep
bitmast_blockcypher/config/__init__.py
bitmast_blockcypher/config/block_cypher.ini
bitmast_blockcypher/config/config.ini
bitmast_blockcypher/config/crypto_currency.ini
bitmast_blockcypher/errors/__init__.py
bitmast_blockcypher/errors/messages.py
bitmast_blockcypher-1.0.3.dist-info/METADATA
bitmast_blockcypher-1.0.3.dist-info/WHEEL
bitmast_blockcypher-1.0.3.dist-info/top_level.txt
bitmast_blockcypher-1.0.3.dist-info/RECORD
