Metadata-Version: 2.1
Name: bitmast-blockcypher
Version: 1.0.3
Summary: Python wrapper for accessing BlockCypher API
Home-page: UNKNOWN
Author: Aniefiok Friday
Author-email: frier17@a17s.co.uk
License: MIT
Platform: UNKNOWN
Classifier: License :: OSI Approved :: MIT License
Classifier: Programming Language :: Python :: 3
Classifier: Programming Language :: Python :: 3.9
Requires-Dist: bitcoinlib
Requires-Dist: blockcypher
Requires-Dist: stringcase
